{
  "$schema": "https://json-schema.org/draft/2020-12/schema",
  "$id": "https://github.com/Coreeple/json-works/json-ph/Model/Schemas/post.json",
  "title": "Post",
  "description": "A post that users cane make.",
  "type": "object",
  "properties": {
    "userId": {
      "type": "integer"
    },
    "id": {
      "type": "integer"
    },
    "title": {
      "type": "string"
    },
    "body": {
      "type": "string"
    }
  },
  "required": [
    "userId",
    "id",
    "title",
    "body"
  ]
}
